{
  "action" : "NEW",
  "eventDate" : "2018-10-01",
  "eventEffect" : {
    "contract" : [ "37f158ab" ],
    "effectedEvent" : "788d6c2c"
  },
  "eventIdentifier" : {
    "identifierValue" : {
      "identifier" : "JYCUYDXDY4"
    }
  },
  "intent" : "NEW_TRADE",
  "party" : [ {
    "legalEntity" : {
      "entityId" : "027300P01DF7BB67DP86",
      "name" : "CCP-P01"
    },
    "partyId" : [ "5264151754007" ],
    "partyIdScheme" : "http://www.fpml.org/coding-scheme/external/iso17442"
  }, {
    "legalEntity" : {
      "entityId" : "845900C02P22NDH4QD17",
      "name" : "CLIENT-C02"
    },
    "partyId" : [ "9512822896080" ],
    "partyIdScheme" : "http://www.fpml.org/coding-scheme/external/iso17442"
  } ],
  "primitive" : {
    "newTrade" : [ {
      "contract" : {
        "account" : [ {
          "accountNumber" : "P01547927812",
          "servicingParty" : "027300P01DF7BB67DP86"
        }, {
          "accountNumber" : "C02217748782",
          "servicingParty" : "845900C02P22NDH4QD17"
        } ],
        "contractIdentifier" : [ {
          "identifierValue" : {
            "identifier" : "Q0FBJYNZWN",
            "identifierScheme" : "http://www.fpml.org/coding-scheme/external/unique-transaction-identifier/"
          },
          "version" : 1
        } ],
        "contractualProduct" : {
          "economicTerms" : {
            "payout" : {
              "cashflow" : [ {
                "payerReceiver" : {
                  "payerPartyReference" : "5264151754007",
                  "receiverPartyReference" : "9512822896080"
                },
                "cashflowAmount" : {
                  "amount" : 30000,
                  "currency" : "EUR"
                },
                "rosettaKeyValue" : "77568a52"
              } ],
              "creditDefaultPayout" : {
                "generalTerms" : {
                  "buyerSeller" : {
                    "buyerPartyReference" : "5264151754007",
                    "sellerPartyReference" : "9512822896080"
                  },
                  "dateAdjustments" : {
                    "businessCenters" : {
                      "businessCenter" : [ "EUTA" ]
                    },
                    "businessDayConvention" : "FOLLOWING"
                  },
                  "indexReferenceInformation" : {
                    "indexName" : "iTraxx Europe Crossover Series 29 Version 1",
                    "indexSeries" : 29
                  }
                },
                "protectionTerms" : {
                  "notionalAmount" : {
                    "amount" : 20000000,
                    "currency" : "EUR"
                  }
                },
                "rosettaKeyValue" : "cbde65d0"
              },
              "interestRatePayout" : [ {
                "calculationPeriodDates" : {
                  "effectiveDate" : {
                    "adjustableDate" : {
                      "unadjustedDate" : "2018-10-03"
                    }
                  },
                  "terminationDate" : {
                    "unadjustedDate" : "2020-12-20"
                  }
                },
                "dayCountFraction" : "ACT_360",
                "interestRate" : {
                  "fixedRate" : {
                    "initialValue" : 0.050000
                  }
                },
                "payerReceiver" : {
                  "payerPartyReference" : "5264151754007",
                  "receiverPartyReference" : "9512822896080"
                },
                "quantity" : {
                  "notionalSchedule" : {
                    "notionalStepSchedule" : {
                      "initialValue" : 20000000,
                      "currency" : "EUR"
                    }
                  }
                },
                "rosettaKeyValue" : "44ad1468"
              } ]
            },
            "rosettaKeyValue" : "1e9c26d6"
          },
          "productIdentification" : {
            "primaryAssetClass" : "CREDIT",
            "productQualifier" : "Credit_Default_Swap_Index"
          }
        },
        "tradeDate" : {
          "adjustableDate" : {
            "unadjustedDate" : "2018-10-01"
          }
        },
        "rosettaKey" : "37f158ab"
      }
    } ]
  },
  "timestamp" : {
    "creationTimestamp" : "2018-10-01T21:40:55.164"
  },
  "rosettaKey" : "788d6c2c"
}