{
  "action" : "NEW",
  "eventDate" : "2018-10-24",
  "eventEffect" : {
    "contract" : [ "c64ea808" ],
    "effectedEvent" : "5995cd17"
  },
  "eventIdentifier" : {
    "identifierValue" : {
      "identifier" : "GNFTH6TMH5"
    }
  },
  "intent" : "NEW_TRADE",
  "party" : [ {
    "legalEntity" : {
      "entityId" : "444100D02FKCOHSINA94",
      "name" : "DEALER-D02"
    },
    "partyId" : [ "6444838468414" ],
    "partyIdScheme" : "http://www.fpml.org/coding-scheme/external/iso17442"
  }, {
    "legalEntity" : {
      "entityId" : "027300P01DF7BB67DP86",
      "name" : "CCP-P01"
    },
    "partyId" : [ "5264151754007" ],
    "partyIdScheme" : "http://www.fpml.org/coding-scheme/external/iso17442"
  } ],
  "primitive" : {
    "newTrade" : [ {
      "contract" : {
        "account" : [ {
          "accountNumber" : "D02691708843",
          "servicingParty" : "444100D02FKCOHSINA94"
        }, {
          "accountNumber" : "P01547927812",
          "servicingParty" : "027300P01DF7BB67DP86"
        } ],
        "contractIdentifier" : [ {
          "identifierValue" : {
            "identifier" : "FTQJWTPK3D",
            "identifierScheme" : "http://www.fpml.org/coding-scheme/external/unique-transaction-identifier/"
          },
          "version" : 1
        } ],
        "contractualProduct" : {
          "economicTerms" : {
            "payout" : {
              "cashflow" : [ {
                "payerReceiver" : {
                  "payerPartyReference" : "6444838468414",
                  "receiverPartyReference" : "5264151754007"
                },
                "cashflowAmount" : {
                  "amount" : 40000,
                  "currency" : "USD"
                },
                "rosettaKeyValue" : "9ead0426"
              } ],
              "creditDefaultPayout" : {
                "generalTerms" : {
                  "buyerSeller" : {
                    "buyerPartyReference" : "6444838468414",
                    "sellerPartyReference" : "5264151754007"
                  },
                  "dateAdjustments" : {
                    "businessCenters" : {
                      "businessCenter" : [ "USNY" ]
                    },
                    "businessDayConvention" : "FOLLOWING"
                  },
                  "indexReferenceInformation" : {
                    "indexName" : "CDX.NA.HY",
                    "indexSeries" : 30
                  }
                },
                "protectionTerms" : {
                  "notionalAmount" : {
                    "amount" : 30000000,
                    "currency" : "USD"
                  }
                },
                "rosettaKeyValue" : "1fc752f5"
              },
              "interestRatePayout" : [ {
                "calculationPeriodDates" : {
                  "effectiveDate" : {
                    "adjustableDate" : {
                      "unadjustedDate" : "2018-10-26"
                    }
                  },
                  "terminationDate" : {
                    "unadjustedDate" : "2023-12-20"
                  }
                },
                "dayCountFraction" : "ACT_360",
                "interestRate" : {
                  "fixedRate" : {
                    "initialValue" : 0.050000
                  }
                },
                "payerReceiver" : {
                  "payerPartyReference" : "6444838468414",
                  "receiverPartyReference" : "5264151754007"
                },
                "quantity" : {
                  "notionalSchedule" : {
                    "notionalStepSchedule" : {
                      "initialValue" : 30000000,
                      "currency" : "USD"
                    }
                  }
                },
                "rosettaKeyValue" : "a5ca74ed"
              } ]
            },
            "rosettaKeyValue" : "a6d85482"
          },
          "productIdentification" : {
            "primaryAssetClass" : "CREDIT",
            "productQualifier" : "Credit_Default_Swap_Index"
          }
        },
        "tradeDate" : {
          "adjustableDate" : {
            "unadjustedDate" : "2018-10-24"
          }
        },
        "rosettaKey" : "c64ea808"
      }
    } ]
  },
  "timestamp" : {
    "creationTimestamp" : "2018-10-24T21:40:57.418"
  },
  "rosettaKey" : "5995cd17"
}