{
  "action" : "NEW",
  "eventDate" : "2018-10-09",
  "eventEffect" : {
    "contract" : [ "5cb7529a" ],
    "effectedEvent" : "c8126d5c"
  },
  "eventIdentifier" : {
    "identifierValue" : {
      "identifier" : "RMXXM2H5EU"
    }
  },
  "intent" : "NEW_TRADE",
  "party" : [ {
    "legalEntity" : {
      "entityId" : "027300P01DF7BB67DP86",
      "name" : "CCP-P01"
    },
    "partyId" : [ "5264151754007" ],
    "partyIdScheme" : "http://www.fpml.org/coding-scheme/external/iso17442"
  }, {
    "legalEntity" : {
      "entityId" : "272200D03NJCEDFEOB38",
      "name" : "DEALER-D03"
    },
    "partyId" : [ "1678822845845" ],
    "partyIdScheme" : "http://www.fpml.org/coding-scheme/external/iso17442"
  } ],
  "primitive" : {
    "newTrade" : [ {
      "contract" : {
        "account" : [ {
          "accountNumber" : "P01547927812",
          "servicingParty" : "027300P01DF7BB67DP86"
        }, {
          "accountNumber" : "D03934176151",
          "servicingParty" : "272200D03NJCEDFEOB38"
        } ],
        "contractIdentifier" : [ {
          "identifierValue" : {
            "identifier" : "HWS3HISO0A",
            "identifierScheme" : "http://www.fpml.org/coding-scheme/external/unique-transaction-identifier/"
          },
          "version" : 1
        } ],
        "contractualProduct" : {
          "economicTerms" : {
            "payout" : {
              "interestRatePayout" : [ {
                "calculationPeriodDates" : {
                  "calculationPeriodDatesAdjustments" : {
                    "businessCenters" : {
                      "businessCenter" : [ "USNY" ]
                    },
                    "businessDayConvention" : "FOLLOWING"
                  },
                  "calculationPeriodFrequency" : {
                    "period" : "M",
                    "periodMultiplier" : 3,
                    "rollConvention" : "_3"
                  },
                  "effectiveDate" : {
                    "adjustableDate" : {
                      "dateAdjustments" : {
                        "businessCenters" : {
                          "businessCenter" : [ "USNY" ]
                        },
                        "businessDayConvention" : "FOLLOWING"
                      },
                      "unadjustedDate" : "2018-10-11"
                    }
                  },
                  "id" : "floatingCalcPeriodDates",
                  "terminationDate" : {
                    "adjustedDate" : "2020-10-13",
                    "dateAdjustments" : {
                      "businessCenters" : {
                        "businessCenter" : [ "USNY" ]
                      },
                      "businessDayConvention" : "FOLLOWING"
                    },
                    "unadjustedDate" : "2020-10-11"
                  }
                },
                "dayCountFraction" : "_30_360",
                "interestRate" : {
                  "floatingRate" : {
                    "floatingRateIndex" : "USD_LIBOR_BBA",
                    "indexTenor" : {
                      "period" : "M",
                      "periodMultiplier" : 3
                    },
                    "spreadSchedule" : [ {
                      "initialValue" : 0.002000
                    } ],
                    "initialRate" : 0.029822
                  }
                },
                "payerReceiver" : {
                  "payerPartyReference" : "5264151754007",
                  "receiverPartyReference" : "1678822845845"
                },
                "paymentDates" : {
                  "calculationPeriodDatesReference" : "floatingCalcPeriodDates",
                  "payRelativeTo" : "CALCULATION_PERIOD_END_DATE",
                  "paymentDatesAdjustments" : {
                    "businessCenters" : {
                      "businessCenter" : [ "USNY" ]
                    },
                    "businessDayConvention" : "FOLLOWING"
                  },
                  "paymentFrequency" : {
                    "period" : "M",
                    "periodMultiplier" : 3
                  }
                },
                "quantity" : {
                  "notionalSchedule" : {
                    "notionalStepSchedule" : {
                      "initialValue" : 500000000.00,
                      "currency" : "USD"
                    }
                  }
                },
                "resetDates" : {
                  "calculationPeriodDatesReference" : "floatingCalcPeriodDates",
                  "fixingDates" : {
                    "period" : "D",
                    "periodMultiplier" : -2,
                    "dayType" : "BUSINESS",
                    "businessCenters" : {
                      "businessCenter" : [ "GBLO" ]
                    },
                    "businessDayConvention" : "NONE",
                    "dateRelativeTo" : "resetDates"
                  },
                  "id" : "resetDates",
                  "resetDatesAdjustments" : {
                    "businessCenters" : {
                      "businessCenter" : [ "GBLO" ]
                    },
                    "businessDayConvention" : "FOLLOWING"
                  },
                  "resetFrequency" : {
                    "period" : "M",
                    "periodMultiplier" : 3
                  },
                  "resetRelativeTo" : "CALCULATION_PERIOD_START_DATE"
                },
                "rosettaKeyValue" : "341d6967"
              }, {
                "calculationPeriodDates" : {
                  "calculationPeriodDatesAdjustments" : {
                    "businessCenters" : {
                      "businessCenter" : [ "USNY" ]
                    },
                    "businessDayConvention" : "FOLLOWING"
                  },
                  "calculationPeriodFrequency" : {
                    "period" : "M",
                    "periodMultiplier" : 6,
                    "rollConvention" : "_3"
                  },
                  "effectiveDate" : {
                    "adjustableDate" : {
                      "dateAdjustments" : {
                        "businessCenters" : {
                          "businessCenter" : [ "USNY" ]
                        },
                        "businessDayConvention" : "FOLLOWING"
                      },
                      "unadjustedDate" : "2018-10-11"
                    }
                  },
                  "id" : "fixedCalcPeriodDates",
                  "terminationDate" : {
                    "adjustedDate" : "2020-10-13",
                    "dateAdjustments" : {
                      "businessCenters" : {
                        "businessCenter" : [ "USNY" ]
                      },
                      "businessDayConvention" : "FOLLOWING"
                    },
                    "unadjustedDate" : "2020-10-11"
                  }
                },
                "dayCountFraction" : "_30_360",
                "interestRate" : {
                  "fixedRate" : {
                    "initialValue" : 0.020439
                  }
                },
                "payerReceiver" : {
                  "payerPartyReference" : "1678822845845",
                  "receiverPartyReference" : "5264151754007"
                },
                "paymentDates" : {
                  "calculationPeriodDatesReference" : "fixedCalcPeriodDates",
                  "payRelativeTo" : "CALCULATION_PERIOD_END_DATE",
                  "paymentDatesAdjustments" : {
                    "businessCenters" : {
                      "businessCenter" : [ "USNY" ]
                    },
                    "businessDayConvention" : "FOLLOWING"
                  },
                  "paymentFrequency" : {
                    "period" : "M",
                    "periodMultiplier" : 6
                  }
                },
                "quantity" : {
                  "notionalSchedule" : {
                    "notionalStepSchedule" : {
                      "initialValue" : 500000000.00,
                      "currency" : "USD"
                    }
                  }
                },
                "rosettaKeyValue" : "56c7d32a"
              } ]
            },
            "rosettaKeyValue" : "d1c2558f"
          },
          "productIdentification" : {
            "primaryAssetClass" : "INTEREST_RATE",
            "productQualifier" : "InterestRate_IRSwap_FixedFloat"
          }
        },
        "tradeDate" : {
          "adjustableDate" : {
            "unadjustedDate" : "2018-10-09"
          }
        },
        "rosettaKey" : "5cb7529a"
      }
    } ]
  },
  "timestamp" : {
    "creationTimestamp" : "2018-10-09T21:40:56.044"
  },
  "rosettaKey" : "c8126d5c"
}