{
  "action" : "NEW",
  "eventDate" : "2018-10-05",
  "eventEffect" : {
    "contract" : [ "918037f7" ],
    "effectedEvent" : "64c71927"
  },
  "eventIdentifier" : {
    "identifierValue" : {
      "identifier" : "EFRR6JSQG4"
    }
  },
  "intent" : "NEW_TRADE",
  "party" : [ {
    "legalEntity" : {
      "entityId" : "027300P01DF7BB67DP86",
      "name" : "CCP-P01"
    },
    "partyId" : [ "5264151754007" ],
    "partyIdScheme" : "http://www.fpml.org/coding-scheme/external/iso17442"
  }, {
    "legalEntity" : {
      "entityId" : "709100D01PQ7HQVZDA69",
      "name" : "DEALER-D01"
    },
    "partyId" : [ "4305743651100" ],
    "partyIdScheme" : "http://www.fpml.org/coding-scheme/external/iso17442"
  } ],
  "primitive" : {
    "newTrade" : [ {
      "contract" : {
        "account" : [ {
          "accountNumber" : "P01547927812",
          "servicingParty" : "027300P01DF7BB67DP86"
        }, {
          "accountNumber" : "D01588595052",
          "servicingParty" : "709100D01PQ7HQVZDA69"
        } ],
        "contractIdentifier" : [ {
          "identifierValue" : {
            "identifier" : "YE9UQTNZEK",
            "identifierScheme" : "http://www.fpml.org/coding-scheme/external/unique-transaction-identifier/"
          },
          "version" : 1
        } ],
        "contractualProduct" : {
          "economicTerms" : {
            "payout" : {
              "cashflow" : [ {
                "payerReceiver" : {
                  "payerPartyReference" : "5264151754007",
                  "receiverPartyReference" : "4305743651100"
                },
                "cashflowAmount" : {
                  "amount" : 10000,
                  "currency" : "USD"
                },
                "rosettaKeyValue" : "2b4aa6f6"
              } ],
              "creditDefaultPayout" : {
                "generalTerms" : {
                  "buyerSeller" : {
                    "buyerPartyReference" : "5264151754007",
                    "sellerPartyReference" : "4305743651100"
                  },
                  "dateAdjustments" : {
                    "businessCenters" : {
                      "businessCenter" : [ "USNY" ]
                    },
                    "businessDayConvention" : "FOLLOWING"
                  },
                  "indexReferenceInformation" : {
                    "indexName" : "CDX.NA.HY",
                    "indexSeries" : 30
                  }
                },
                "protectionTerms" : {
                  "notionalAmount" : {
                    "amount" : 25000000,
                    "currency" : "USD"
                  }
                },
                "rosettaKeyValue" : "112a7b5"
              },
              "interestRatePayout" : [ {
                "calculationPeriodDates" : {
                  "effectiveDate" : {
                    "adjustableDate" : {
                      "unadjustedDate" : "2018-10-09"
                    }
                  },
                  "terminationDate" : {
                    "unadjustedDate" : "2019-12-20"
                  }
                },
                "dayCountFraction" : "ACT_360",
                "interestRate" : {
                  "fixedRate" : {
                    "initialValue" : 0.050000
                  }
                },
                "payerReceiver" : {
                  "payerPartyReference" : "5264151754007",
                  "receiverPartyReference" : "4305743651100"
                },
                "quantity" : {
                  "notionalSchedule" : {
                    "notionalStepSchedule" : {
                      "initialValue" : 25000000,
                      "currency" : "USD"
                    }
                  }
                },
                "rosettaKeyValue" : "3e06551e"
              } ]
            },
            "rosettaKeyValue" : "6e274a61"
          },
          "productIdentification" : {
            "primaryAssetClass" : "CREDIT",
            "productQualifier" : "Credit_Default_Swap_Index"
          }
        },
        "tradeDate" : {
          "adjustableDate" : {
            "unadjustedDate" : "2018-10-05"
          }
        },
        "rosettaKey" : "918037f7"
      }
    } ]
  },
  "timestamp" : {
    "creationTimestamp" : "2018-10-05T21:40:55.613"
  },
  "rosettaKey" : "64c71927"
}