{
  "action" : "NEW",
  "eventDate" : "2018-10-19",
  "eventEffect" : {
    "contract" : [ "df18b7d5" ],
    "effectedEvent" : "22ffe238"
  },
  "eventIdentifier" : {
    "identifierValue" : {
      "identifier" : "EXWPRY35A6"
    }
  },
  "intent" : "NEW_TRADE",
  "party" : [ {
    "legalEntity" : {
      "entityId" : "444100D02FKCOHSINA94",
      "name" : "DEALER-D02"
    },
    "partyId" : [ "5828082809415" ],
    "partyIdScheme" : "http://www.fpml.org/coding-scheme/external/iso17442"
  }, {
    "legalEntity" : {
      "entityId" : "502900C05HITOOMU1P35",
      "name" : "CLIENT-C05"
    },
    "partyId" : [ "3642822994727" ],
    "partyIdScheme" : "http://www.fpml.org/coding-scheme/external/iso17442"
  } ],
  "primitive" : {
    "newTrade" : [ {
      "contract" : {
        "account" : [ {
          "accountNumber" : "D02024214214",
          "servicingParty" : "444100D02FKCOHSINA94"
        }, {
          "accountNumber" : "C05245065949",
          "servicingParty" : "502900C05HITOOMU1P35"
        } ],
        "contractIdentifier" : [ {
          "identifierValue" : {
            "identifier" : "I4WJXJTNIG",
            "identifierScheme" : "http://www.fpml.org/coding-scheme/external/unique-transaction-identifier/"
          },
          "version" : 1
        } ],
        "contractualProduct" : {
          "economicTerms" : {
            "payout" : {
              "interestRatePayout" : [ {
                "calculationPeriodDates" : {
                  "calculationPeriodDatesAdjustments" : {
                    "businessCenters" : {
                      "businessCenter" : [ "USNY" ]
                    },
                    "businessDayConvention" : "FOLLOWING"
                  },
                  "calculationPeriodFrequency" : {
                    "period" : "M",
                    "periodMultiplier" : 3,
                    "rollConvention" : "_3"
                  },
                  "effectiveDate" : {
                    "adjustableDate" : {
                      "adjustedDate" : "2018-10-22",
                      "dateAdjustments" : {
                        "businessCenters" : {
                          "businessCenter" : [ "USNY" ]
                        },
                        "businessDayConvention" : "FOLLOWING"
                      },
                      "unadjustedDate" : "2018-10-21"
                    }
                  },
                  "id" : "floatingCalcPeriodDates",
                  "terminationDate" : {
                    "adjustedDate" : "2023-10-23",
                    "dateAdjustments" : {
                      "businessCenters" : {
                        "businessCenter" : [ "USNY" ]
                      },
                      "businessDayConvention" : "FOLLOWING"
                    },
                    "unadjustedDate" : "2023-10-22"
                  }
                },
                "dayCountFraction" : "ACT_360",
                "interestRate" : {
                  "floatingRate" : {
                    "floatingRateIndex" : "USD_LIBOR_BBA",
                    "indexTenor" : {
                      "period" : "M",
                      "periodMultiplier" : 3
                    },
                    "spreadSchedule" : [ {
                      "initialValue" : 0.001000
                    } ],
                    "initialRate" : 0.025222
                  }
                },
                "payerReceiver" : {
                  "payerPartyReference" : "5828082809415",
                  "receiverPartyReference" : "3642822994727"
                },
                "paymentDates" : {
                  "calculationPeriodDatesReference" : "floatingCalcPeriodDates",
                  "payRelativeTo" : "CALCULATION_PERIOD_END_DATE",
                  "paymentDatesAdjustments" : {
                    "businessCenters" : {
                      "businessCenter" : [ "USNY" ]
                    },
                    "businessDayConvention" : "FOLLOWING"
                  },
                  "paymentFrequency" : {
                    "period" : "M",
                    "periodMultiplier" : 3
                  }
                },
                "quantity" : {
                  "notionalSchedule" : {
                    "notionalStepSchedule" : {
                      "initialValue" : 700000000.00,
                      "currency" : "USD"
                    }
                  }
                },
                "resetDates" : {
                  "calculationPeriodDatesReference" : "floatingCalcPeriodDates",
                  "fixingDates" : {
                    "period" : "D",
                    "periodMultiplier" : -2,
                    "dayType" : "BUSINESS",
                    "businessCenters" : {
                      "businessCenter" : [ "GBLO" ]
                    },
                    "businessDayConvention" : "NONE",
                    "dateRelativeTo" : "resetDates"
                  },
                  "id" : "resetDates",
                  "resetDatesAdjustments" : {
                    "businessCenters" : {
                      "businessCenter" : [ "GBLO" ]
                    },
                    "businessDayConvention" : "FOLLOWING"
                  },
                  "resetFrequency" : {
                    "period" : "M",
                    "periodMultiplier" : 3
                  },
                  "resetRelativeTo" : "CALCULATION_PERIOD_START_DATE"
                },
                "rosettaKeyValue" : "d9fb2ffd"
              }, {
                "calculationPeriodDates" : {
                  "calculationPeriodDatesAdjustments" : {
                    "businessCenters" : {
                      "businessCenter" : [ "USNY" ]
                    },
                    "businessDayConvention" : "FOLLOWING"
                  },
                  "calculationPeriodFrequency" : {
                    "period" : "M",
                    "periodMultiplier" : 6,
                    "rollConvention" : "_3"
                  },
                  "effectiveDate" : {
                    "adjustableDate" : {
                      "adjustedDate" : "2018-10-22",
                      "dateAdjustments" : {
                        "businessCenters" : {
                          "businessCenter" : [ "USNY" ]
                        },
                        "businessDayConvention" : "FOLLOWING"
                      },
                      "unadjustedDate" : "2018-10-21"
                    }
                  },
                  "id" : "floatingCalcPeriodDates",
                  "terminationDate" : {
                    "adjustedDate" : "2023-10-23",
                    "dateAdjustments" : {
                      "businessCenters" : {
                        "businessCenter" : [ "USNY" ]
                      },
                      "businessDayConvention" : "FOLLOWING"
                    },
                    "unadjustedDate" : "2023-10-22"
                  }
                },
                "dayCountFraction" : "ACT_360",
                "interestRate" : {
                  "floatingRate" : {
                    "floatingRateIndex" : "USD_LIBOR_BBA",
                    "indexTenor" : {
                      "period" : "M",
                      "periodMultiplier" : 6
                    },
                    "spreadSchedule" : [ {
                      "initialValue" : 0.003000
                    } ],
                    "initialRate" : 0.032151
                  }
                },
                "payerReceiver" : {
                  "payerPartyReference" : "3642822994727",
                  "receiverPartyReference" : "5828082809415"
                },
                "paymentDates" : {
                  "calculationPeriodDatesReference" : "floatingCalcPeriodDates",
                  "payRelativeTo" : "CALCULATION_PERIOD_END_DATE",
                  "paymentDatesAdjustments" : {
                    "businessCenters" : {
                      "businessCenter" : [ "USNY" ]
                    },
                    "businessDayConvention" : "FOLLOWING"
                  },
                  "paymentFrequency" : {
                    "period" : "M",
                    "periodMultiplier" : 6
                  }
                },
                "quantity" : {
                  "notionalSchedule" : {
                    "notionalStepSchedule" : {
                      "initialValue" : 700000000.00,
                      "currency" : "USD"
                    }
                  }
                },
                "resetDates" : {
                  "calculationPeriodDatesReference" : "floatingCalcPeriodDates",
                  "fixingDates" : {
                    "period" : "D",
                    "periodMultiplier" : -2,
                    "dayType" : "BUSINESS",
                    "businessCenters" : {
                      "businessCenter" : [ "GBLO" ]
                    },
                    "businessDayConvention" : "NONE",
                    "dateRelativeTo" : "resetDates"
                  },
                  "id" : "resetDates",
                  "resetDatesAdjustments" : {
                    "businessCenters" : {
                      "businessCenter" : [ "GBLO" ]
                    },
                    "businessDayConvention" : "FOLLOWING"
                  },
                  "resetFrequency" : {
                    "period" : "M",
                    "periodMultiplier" : 6
                  },
                  "resetRelativeTo" : "CALCULATION_PERIOD_START_DATE"
                },
                "rosettaKeyValue" : "de0fd1d8"
              } ]
            },
            "rosettaKeyValue" : "495538cb"
          },
          "productIdentification" : {
            "primaryAssetClass" : "INTEREST_RATE",
            "productQualifier" : "InterestRate_IRSwap_Basis"
          }
        },
        "tradeDate" : {
          "adjustableDate" : {
            "unadjustedDate" : "2018-10-19"
          }
        },
        "rosettaKey" : "df18b7d5"
      }
    } ]
  },
  "timestamp" : {
    "creationTimestamp" : "2018-10-19T21:40:56.903"
  },
  "rosettaKey" : "22ffe238"
}